fastscheduler/__init__.py
fastscheduler/fastapi_integration.py
fastscheduler/main.py
fastscheduler/models.py
fastscheduler/schedulers.py
fastscheduler/storage/__init__.py
fastscheduler/storage/base.py
fastscheduler/storage/json_backend.py
fastscheduler/storage/models.py
fastscheduler/storage/sqlmodel_backend.py
fastscheduler/templates/dashboard.html
fastscheduler-0.2.0.dist-info/METADATA
fastscheduler-0.2.0.dist-info/WHEEL
fastscheduler-0.2.0.dist-info/licenses/LICENSE
fastscheduler-0.2.0.dist-info/RECORD
