Metadata-Version: 2.4
Name: fastscheduler
Version: 0.2.0
Summary: Simple, lightweight task scheduler for Python with async support
Project-URL: Repository, https://github.com/MichielMe/fastscheduler
Author-email: Michiel Meire <michiel.meire1@gmail.com>
License: MIT
License-File: LICENSE
Keywords: async,background,cron,jobs,scheduler,task
Classifier: Development Status :: 4 - Beta
Classifier: Intended Audience :: Developers
Classifier: License :: OSI Approved :: MIT License
Classifier: Operating System :: OS Independent
Classifier: Programming Language :: Python :: 3
Classifier: Programming Language :: Python :: 3.10
Classifier: Programming Language :: Python :: 3.11
Classifier: Programming Language :: Python :: 3.12
Classifier: Programming Language :: Python :: 3.13
Classifier: Topic :: Software Development :: Libraries :: Python Modules
Classifier: Topic :: System :: Systems Administration
Requires-Python: >=3.10
Requires-Dist: sqlmodel>=0.0.31
Provides-Extra: all
Requires-Dist: croniter>=2.0.0; extra == 'all'
Requires-Dist: fastapi[standard]>=0.100.0; extra == 'all'
Requires-Dist: sqlmodel>=0.0.18; extra == 'all'
Provides-Extra: cron
Requires-Dist: croniter>=2.0.0; extra == 'cron'
Provides-Extra: database
Requires-Dist: sqlmodel>=0.0.18; extra == 'database'
Provides-Extra: fastapi
Requires-Dist: fastapi[standard]>=0.100.0; extra == 'fastapi'
